seabred/__init__.py
seabred/plotting.py
seabred-0.0.1.dist-info/LICENSE
seabred-0.0.1.dist-info/METADATA
seabred-0.0.1.dist-info/WHEEL
seabred-0.0.1.dist-info/top_level.txt
seabred-0.0.1.dist-info/RECORD
