Metadata-Version: 2.1
Name: seabred
Version: 0.0.1
Summary: Seaborn-like plots for numpy arrays
Home-page: https://github.com/jtebert/seabred
Author: Julia Ebert
Author-email: julia@juliaebert.com
License: UNKNOWN
Platform: UNKNOWN
Classifier: Development Status :: 1 - Planning
Classifier: Programming Language :: Python :: 3
Classifier: License :: OSI Approved :: MIT License
Classifier: Operating System :: OS Independent
Requires-Dist: numpy
Requires-Dist: matplotlib
